agent_stream/__init__.py
agent_stream/filters/__init__.py
agent_stream/filters/autogen.py
agent_stream/filters/filters.py
agent_stream/managers/__init__.py
agent_stream/managers/rabbitmq.py
agent_stream/streams/__init__.py
agent_stream/streams/rabbitmq.py
agent_stream/streams/sse.py
agent_stream-0.2.0.dist-info/METADATA
agent_stream-0.2.0.dist-info/WHEEL
agent_stream-0.2.0.dist-info/licenses/LICENSE
agent_stream-0.2.0.dist-info/RECORD
