Metadata-Version: 2.4
Name: agent_stream
Version: 0.2.0
Summary: Streaming utilities for agent/LLM systems (RabbitMQ, etc.)
Project-URL: Homepage, https://github.com/Cognitive-Stack/agent-stream
Project-URL: Repository, https://github.com/Cognitive-Stack/agent-stream
Project-URL: Issues, https://github.com/Cognitive-Stack/agent-stream/issues
Author-email: Hieu TRAN <hieutrantrung.it@gmail.com>
License: MIT License
License-File: LICENSE
Keywords: AI,LLM,RabbitMQ,agent,autogen,filters,message,realtime,sse,streaming
Classifier: Intended Audience :: Developers
Classifier: License :: OSI Approved :: MIT License
Classifier: Operating System :: OS Independent
Classifier: Programming Language :: Python :: 3
Classifier: Programming Language :: Python :: 3.10
Classifier: Programming Language :: Python :: 3.11
Classifier: Programming Language :: Python :: 3.12
Classifier: Topic :: Communications
Classifier: Topic :: Software Development :: Libraries
Classifier: Topic :: System :: Distributed Computing
Requires-Python: <4.0,>=3.10
Requires-Dist: aio-pika>=9.3.0
Requires-Dist: autogen-agentchat<0.6.0,>=0.5.7
Requires-Dist: autogen-core<0.6.0,>=0.5.7
